[
{"prodDescCode":"BEH","productDesc":"BEHRINGER"},
{"prodDescCode":"BOS","productDesc":"BOSS"},
{"prodDescCode":"CAS","productDesc":"CASIO"},
{"prodDescCode":"COR","productDesc":"CORT"},
{"prodDescCode":"EPI","productDesc":"EPIPHONE"},
{"prodDescCode":"FEN","productDesc":"FENDER"},
{"prodDescCode":"GIL","productDesc":"GIBSON"},
{"prodDescCode":"HOF","productDesc":"HOFNER"},
{"prodDescCode":"IBA","productDesc":"IBANEZ"},
{"prodDescCode":"JBL","productDesc":"JBL"},
{"prodDescCode":"KAW","productDesc":"KAWAI"},
{"prodDescCode":"KOR","productDesc":"KORG"},
{"prodDescCode":"LUD","productDesc":"LUDWIG"},
{"prodDescCode":"MAR","productDesc":"MARSHALL"},
{"prodDescCode":"MED","productDesc":"MEDELI"},
{"prodDescCode":"OVA","productDesc":"OVATION"},
{"prodDescCode":"PAI","productDesc":"PAISTE"},
{"prodDescCode":"PEA","productDesc":"PEARL"},
{"prodDescCode":"PEV","productDesc":"PEAVEY"},
{"prodDescCode":"PET","productDesc":"PETROF"},
{"prodDescCode":"PRE","productDesc":"PREMIER"},
{"prodDescCode":"PRI","productDesc":"PRINCE"},
{"prodDescCode":"ROL","productDesc":"ROLAND"},
{"prodDescCode":"RUS","productDesc":"RUSSEL"},
{"prodDescCode":"SAB","productDesc":"SABIAN"},
{"prodDescCode":"SMK","productDesc":"SAMICK"},
{"prodDescCode":"SEN","productDesc":"SENNHEISER"},
{"prodDescCode":"TAK","productDesc":"TAKAMINE"},
{"prodDescCode":"TAM","productDesc":"TAMA"},
{"prodDescCode":"TEC","productDesc":"TECHNICS"},
{"prodDescCode":"TOR","productDesc":"TORNADO"},
{"prodDescCode":"YAM","productDesc":"YAMAHA"},
{"prodDescCode":"ZIL","productDesc":"ZILDJIAN"},
{"prodDescCode":"MUOT","productDesc":"OTHER"}
]